Metadata-Version: 2.1
Name: django-ief
Version: 0.1.0
Summary: A model field that can be edited without needing a form.
Home-page: https://github.com/isik-kaplan/django_ief
Author: isik-kaplan
Author-email: 
License: APGL-3.0
Platform: UNKNOWN
Requires-Python: >=3.5
